{
  "configVersion": 1,
  "timestamp": 1591477170123,
  "index": "/index.html",
  "assetGroups": [
    {
      "name": "app",
      "installMode": "prefetch",
      "updateMode": "prefetch",
      "urls": [
        "/1-es2015.2d98b31b3ec9c393779a.js",
        "/1-es2015.bb81aed2398c7702f856.js",
        "/1-es5.2d98b31b3ec9c393779a.js",
        "/1-es5.bb81aed2398c7702f856.js",
        "/6-es2015.bf0d4e057ea2c9518401.js",
        "/6-es5.bf0d4e057ea2c9518401.js",
        "/7-es2015.9bf5f45784c9220d4893.js",
        "/7-es2015.ba620da84db5ce96fe94.js",
        "/7-es5.9bf5f45784c9220d4893.js",
        "/7-es5.ba620da84db5ce96fe94.js",
        "/8-es2015.1885de318074452f648d.js",
        "/8-es2015.c0940a79ea5a94e28920.js",
        "/8-es5.1885de318074452f648d.js",
        "/8-es5.c0940a79ea5a94e28920.js",
        "/9-es2015.1d0605a4931079e3b7ae.js",
        "/9-es5.1d0605a4931079e3b7ae.js",
        "/common-es2015.a44c8c21f1e6a98a2ed4.js",
        "/common-es5.a44c8c21f1e6a98a2ed4.js",
        "/favicon.ico",
        "/index.html",
        "/main-es2015.45ed77716cf8ee82cc20.js",
        "/main-es2015.b41c547fd79ef056201a.js",
        "/main-es2015.e603a1d13bd403a69064.js",
        "/main-es5.45ed77716cf8ee82cc20.js",
        "/main-es5.b41c547fd79ef056201a.js",
        "/main-es5.e603a1d13bd403a69064.js",
        "/manifest.webmanifest",
        "/ngsw-worker.js",
        "/polyfills-es2015.ae2ff135b6a0a9cb55e7.js",
        "/polyfills-es2015.b1b4539dab1840335945.js",
        "/polyfills-es5.86f7ad57e8b901d60e04.js",
        "/polyfills-es5.b43423c6d88aefbdc291.js",
        "/runtime-es2015.11e8a8ddd6a892f3977d.js",
        "/runtime-es2015.a7cb340b29614452699f.js",
        "/runtime-es5.11e8a8ddd6a892f3977d.js",
        "/runtime-es5.a7cb340b29614452699f.js",
        "/safety-worker.js",
        "/styles.19d5356675cdb9147ea2.css",
        "/worker-basic.min.js"
      ],
      "patterns": []
    },
    {
      "name": "assets",
      "installMode": "lazy",
      "updateMode": "prefetch",
      "urls": [
        "/assets/icons/icon-128x128.png",
        "/assets/icons/icon-144x144.png",
        "/assets/icons/icon-152x152.png",
        "/assets/icons/icon-192x192.png",
        "/assets/icons/icon-384x384.png",
        "/assets/icons/icon-512x512.png",
        "/assets/icons/icon-72x72.png",
        "/assets/icons/icon-96x96.png",
        "/glyphicons-halflings-regular.060b2710bdbbe3dfe48b.svg",
        "/glyphicons-halflings-regular.4692b9ec53fd5972caa2.ttf",
        "/glyphicons-halflings-regular.5be1347c682810f199c7.eot",
        "/glyphicons-halflings-regular.82b1212e45a2bc35dd73.woff",
        "/glyphicons-halflings-regular.be810be3a3e14c682a25.woff2"
      ],
      "patterns": []
    }
  ],
  "dataGroups": [
    {
      "name": "recipes",
      "patterns": [
        "https:\\/\\/dkorolev-ng-cource-project\\.firebaseio\\.com\\/.*"
      ],
      "strategy": "performance",
      "maxSize": 5,
      "maxAge": 18000000,
      "timeoutMs": 10000,
      "version": 1
    }
  ],
  "hashTable": {
    "/1-es2015.2d98b31b3ec9c393779a.js": "ddb127084c291a603bcce735d1ebc51f2ca21ea4",
    "/1-es2015.bb81aed2398c7702f856.js": "267d3190f7b302d6cf346c39e5a1d91da4b8a7b0",
    "/1-es5.2d98b31b3ec9c393779a.js": "4374a815fddc9313bfd853f310d7b719c3da9345",
    "/1-es5.bb81aed2398c7702f856.js": "b613c05d46e484b16bbd1eab215d3fcc2b73de6c",
    "/6-es2015.bf0d4e057ea2c9518401.js": "5e450bf8518077417d44f056e1ab0b1621d0a782",
    "/6-es5.bf0d4e057ea2c9518401.js": "4a5854b4862e309503d0335f51001f07cca83ba7",
    "/7-es2015.9bf5f45784c9220d4893.js": "0e54e2116cf336329bb868a253ffe67f8a3691af",
    "/7-es2015.ba620da84db5ce96fe94.js": "0c44d722555696f8003f370f02429b31adb533a5",
    "/7-es5.9bf5f45784c9220d4893.js": "b109266eda0dcae991efc96fe2e7793202f9abef",
    "/7-es5.ba620da84db5ce96fe94.js": "4f24c3367730d118b068e44032c7776139aaa1db",
    "/8-es2015.1885de318074452f648d.js": "10176c8e490b2c0a7124538ff49458519c9a1fba",
    "/8-es2015.c0940a79ea5a94e28920.js": "4dfd95d8d1824596605c3c81a94aeb753deca9b4",
    "/8-es5.1885de318074452f648d.js": "18d81732812b542036f5cfa12e978d91329da353",
    "/8-es5.c0940a79ea5a94e28920.js": "08cf5cfb1a11997b99988e8fdf9abe3f8f81d53c",
    "/9-es2015.1d0605a4931079e3b7ae.js": "31be0d781bec4ccdeb1881883b20c8dadf0752ae",
    "/9-es5.1d0605a4931079e3b7ae.js": "e0367561aedfee671c418c2cb8b3ee3758c72b02",
    "/assets/icons/icon-128x128.png": "dae3b6ed49bdaf4327b92531d4b5b4a5d30c7532",
    "/assets/icons/icon-144x144.png": "b0bd89982e08f9bd2b642928f5391915b74799a7",
    "/assets/icons/icon-152x152.png": "7479a9477815dfd9668d60f8b3b2fba709b91310",
    "/assets/icons/icon-192x192.png": "1abd80d431a237a853ce38147d8c63752f10933b",
    "/assets/icons/icon-384x384.png": "329749cd6393768d3131ed6304c136b1ca05f2fd",
    "/assets/icons/icon-512x512.png": "559d9c4318b45a1f2b10596bbb4c960fe521dbcc",
    "/assets/icons/icon-72x72.png": "c457e56089a36952cd67156f9996bc4ce54a5ed9",
    "/assets/icons/icon-96x96.png": "3914125a4b445bf111c5627875fc190f560daa41",
    "/common-es2015.a44c8c21f1e6a98a2ed4.js": "e92d3f6bdc9105f61f5bee1b32b443ee8b5ac7af",
    "/common-es5.a44c8c21f1e6a98a2ed4.js": "90c5fba918ddbc728fd4e4dcb8dfa2b5e60adbf1",
    "/favicon.ico": "22f6a4a3bcaafafb0254e0f2fa4ceb89e505e8b2",
    "/glyphicons-halflings-regular.060b2710bdbbe3dfe48b.svg": "de51a8494180a6db074af2dee2383f0a363c5b08",
    "/glyphicons-halflings-regular.4692b9ec53fd5972caa2.ttf": "44bc1850f570972267b169ae18f1cb06b611ffa2",
    "/glyphicons-halflings-regular.5be1347c682810f199c7.eot": "86b6f62b7853e67d3e635f6512a5a5efc58ea3c3",
    "/glyphicons-halflings-regular.82b1212e45a2bc35dd73.woff": "278e49a86e634da6f2a02f3b47dd9d2a8f26210f",
    "/glyphicons-halflings-regular.be810be3a3e14c682a25.woff2": "ca35b697d99cae4d1b60f2d60fcd37771987eb07",
    "/index.html": "befb44265ee244e9afe07db79bfd11d420bf1840",
    "/main-es2015.45ed77716cf8ee82cc20.js": "120146245c628bb46a8635c8159a2ab48247663e",
    "/main-es2015.b41c547fd79ef056201a.js": "5b433052bbef0c1300c487a865882cc702eb2c05",
    "/main-es2015.e603a1d13bd403a69064.js": "4a662bb40d8614f654c72f0cc7ee9b1bca2ea68f",
    "/main-es5.45ed77716cf8ee82cc20.js": "2f467d6465e0bfaee7ec708308644b3e2f9cd873",
    "/main-es5.b41c547fd79ef056201a.js": "0b9c628539c54f0b079b56c8993011a75e3ebcba",
    "/main-es5.e603a1d13bd403a69064.js": "5abee162f575552ac505b1263a41769a37fb641f",
    "/manifest.webmanifest": "8487b55f57ee6f7f150586e5a5ffb0e19525bee7",
    "/ngsw-worker.js": "6670478ee6c59ce3db30f9719d926f178b3c1141",
    "/polyfills-es2015.ae2ff135b6a0a9cb55e7.js": "15a133b6cbb459a66fcd2e75f6aa25782e5d79c4",
    "/polyfills-es2015.b1b4539dab1840335945.js": "c6df5256b53226df1d997d0b146fad0da7c48be3",
    "/polyfills-es5.86f7ad57e8b901d60e04.js": "6fb9b275d5f1484215fde72ba3f10480fa9692a8",
    "/polyfills-es5.b43423c6d88aefbdc291.js": "a60bd2b190335b8cb870fca491c3d3d142f2caae",
    "/runtime-es2015.11e8a8ddd6a892f3977d.js": "e0d3d95ec0409460a995561d4e072a1448cff2f2",
    "/runtime-es2015.a7cb340b29614452699f.js": "5a15f4002ca05fe74beff7bc4e18b12515e0b6b2",
    "/runtime-es5.11e8a8ddd6a892f3977d.js": "5fe68451003b69aeff611ff46775031768c037bc",
    "/runtime-es5.a7cb340b29614452699f.js": "5c768ecbf00bea7ce447ac25f912c51d24b05083",
    "/safety-worker.js": "69091ea3bc657ca553283fac2768aa67c586b372",
    "/styles.19d5356675cdb9147ea2.css": "5868c6ecdcff6a49bcdf2cd2d9773d4d7a8a5695",
    "/worker-basic.min.js": "69091ea3bc657ca553283fac2768aa67c586b372"
  },
  "navigationUrls": [
    {
      "positive": true,
      "regex": "^\\/.*$"
    },
    {
      "positive": false,
      "regex": "^\\/(?:.+\\/)?[^/]*\\.[^/]*$"
    },
    {
      "positive": false,
      "regex": "^\\/(?:.+\\/)?[^/]*__[^/]*$"
    },
    {
      "positive": false,
      "regex": "^\\/(?:.+\\/)?[^/]*__[^/]*\\/.*$"
    }
  ]
}